{"lines":[{"end":"E","id":0,"start":"B"},{"end":"C","id":1,"start":"E"},{"end":"D","id":2,"start":"C"},{"end":"F","id":3,"start":"D"},{"end":"A","id":4,"start":"F"},{"end":"B","id":5,"start":"A"},{"end":"G","id":6,"start":"B"},{"end":"I","id":7,"start":"G"},{"end":"L","id":8,"start":"I"},{"end":"K","id":9,"start":"L"},{"end":"J","id":10,"start":"K"},{"end":"H","id":11,"start":"J"},{"end":"C","id":12,"start":"H"},{"end":"G","id":13,"start":"C"},{"end":"H","id":14,"start":"G"},{"end":"B","id":15,"start":"H"}],"v2":[{"x":30,"id":"A","y":540},{"x":150,"id":"B","y":540},{"x":390,"id":"C","y":540},{"x":510,"id":"D","y":540},{"x":270,"id":"E","y":630},{"x":270,"id":"F","y":720},{"x":150,"id":"G","y":180},{"x":390,"id":"H","y":180},{"x":60,"id":"I","y":180},{"x":480,"id":"J","y":180},{"x":480,"id":"K","y":30},{"x":60,"id":"L","y":30}],"canvas":{"height":750,"width":540},"bid":1,"mid":13,"lid":18}