{"lines":[{"end":"K","id":0,"start":"N"},{"end":"L","id":1,"start":"K"},{"end":"N","id":2,"start":"L"},{"end":"M","id":3,"start":"N"},{"end":"J","id":4,"start":"M"},{"end":"I","id":5,"start":"J"},{"end":"M","id":6,"start":"I"},{"end":"K","id":7,"start":"M"},{"end":"H","id":8,"start":"K"},{"end":"E","id":9,"start":"H"},{"end":"B","id":10,"start":"E"},{"end":"F","id":11,"start":"B"},{"end":"E","id":12,"start":"F"},{"end":"A","id":13,"start":"E"},{"end":"B","id":14,"start":"A"},{"end":"D","id":15,"start":"B"},{"end":"A","id":16,"start":"D"},{"end":"C","id":17,"start":"A"},{"end":"D","id":18,"start":"C"},{"end":"G","id":19,"start":"D"},{"end":"J","id":20,"start":"G"},{"end":"N","id":21,"start":"J"}],"v2":[{"x":30,"id":"A","y":150},{"x":150,"id":"B","y":60},{"x":30,"id":"C","y":450},{"x":150,"id":"D","y":300},{"x":270,"id":"E","y":210},{"x":420,"id":"F","y":60},{"x":150,"id":"G","y":450},{"x":420,"id":"H","y":180},{"x":120,"id":"I","y":570},{"x":270,"id":"J","y":420},{"x":390,"id":"K","y":330},{"x":510,"id":"L","y":180},{"x":390,"id":"M","y":570},{"x":510,"id":"N","y":480}],"canvas":{"height":750,"width":540},"bid":1,"mid":10,"lid":1}