{"lines":[{"end":"D","id":0,"start":"B"},{"end":"F","id":1,"start":"D"},{"end":"A","id":2,"start":"F"},{"end":"E","id":3,"start":"A"},{"end":"D","id":4,"start":"E"},{"end":"C","id":5,"start":"D"},{"end":"B","id":6,"start":"C"},{"end":"A","id":7,"start":"B"},{"end":"C","id":8,"start":"A"}],"v2":[{"x":270,"id":"A","y":30},{"x":510,"id":"B","y":570},{"x":30,"id":"C","y":570},{"x":270,"id":"D","y":480},{"x":210,"id":"E","y":360},{"x":330,"id":"F","y":360}],"canvas":{"height":750,"width":540},"bid":1,"mid":1,"lid":8}